{"title":"Revista.Micromania.Diciembre.2010","uid":6004868,"size":89072857,"categoryP":"other","categoryS":"e_books","magnet":"?xt=urn:btih:05520b0fb13a29fa3ab342d1fead4370339451e2&amp;dn=Revista.Micromania.Diciembre.2010&amp;tr=udp%3A%2F%2Ftracker.openbittorrent.com%3A80&amp;tr=udp%3A%2F%2Fopen.demonii.com%3A1337&amp;tr=udp%3A%2F%2Ftracker.coppersurfer.tk%3A6969&amp;tr=udp%3A%2F%2Fexodus.desync.com%3A6969","seeders":1,"leechers":0,"uploader":"gatasalvaje","files":-1,"time":1291289602,"description":"Revista Micromania Diciembre 2010","torrent":{"xt":"urn:btih:05520b0fb13a29fa3ab342d1fead4370339451e2","amp;dn":"Revista.Micromania.Diciembre.2010","amp;tr":["udp%3A%2F%2Ftracker.openbittorrent.com%3A80","udp%3A%2F%2Fopen.demonii.com%3A1337","udp%3A%2F%2Ftracker.coppersurfer.tk%3A6969","udp%3A%2F%2Fexodus.desync.com%3A6969"],"infoHash":"05520b0fb13a29fa3ab342d1fead4370339451e2","infoHashBuffer":{"type":"Buffer","data":[5,82,11,15,177,58,41,250,58,179,66,209,254,173,67,112,51,148,81,226]},"announce":[],"urlList":[]}}