{"title":"Heroine Brainwash Volume 15 Censored","uid":10202505,"size":2416632444,"categoryP":"porn","categoryS":"movies","magnet":"?xt=urn:btih:0953340a33a9fcd3b8db8e4894d20cd74fc01cb8&amp;dn=Heroine+Brainwash+Volume+15+Censored&amp;tr=udp%3A%2F%2Ftracker.openbittorrent.com%3A80&amp;tr=udp%3A%2F%2Fopen.demonii.com%3A1337&amp;tr=udp%3A%2F%2Ftracker.coppersurfer.tk%3A6969&amp;tr=udp%3A%2F%2Fexodus.desync.com%3A6969","seeders":1,"leechers":0,"uploader":"irealu69","files":-1,"time":1400797685,"description":"Heroine Brainwash Volume 15 Censored\n~~~~~~~~~~~~~~~~~~~~~~~~~~~~~~~~~~~~\n\nScreenshots:\n~~~~~~~~~~~~\n &lt;a href=&quot;\nhttp://picturescream.com/x/clean/fFwT&quot; rel=&quot;nofollow&quot; target=&quot;_NEW&quot;&gt;\nhttp://picturescream.com/x/clean/fFwT&lt;/a&gt;\n &lt;a href=&quot;\nhttp://picturescream.com/x/clean/fFwx&quot; rel=&quot;nofollow&quot; target=&quot;_NEW&quot;&gt;\nhttp://picturescream.com/x/clean/fFwx&lt;/a&gt;\n &lt;a href=&quot;\nhttp://picturescream.com/x/clean/fFwh&quot; rel=&quot;nofollow&quot; target=&quot;_NEW&quot;&gt;\nhttp://picturescream.com/x/clean/fFwh&lt;/a&gt;\n &lt;a href=&quot;\nhttp://picturescream.com/x/clean/fFw5&quot; rel=&quot;nofollow&quot; target=&quot;_NEW&quot;&gt;\nhttp://picturescream.com/x/clean/fFw5&lt;/a&gt;\n &lt;a href=&quot;\nhttp://picturescream.com/x/clean/fFwX&quot; rel=&quot;nofollow&quot; target=&quot;_NEW&quot;&gt;\nhttp://picturescream.com/x/clean/fFwX&lt;/a&gt;\n\n\nVideos Info:\n~~~~~~~~~~~~\nSize: 2.25 GB\nResolution: 856x480","torrent":{"xt":"urn:btih:0953340a33a9fcd3b8db8e4894d20cd74fc01cb8","amp;dn":"Heroine+Brainwash+Volume+15+Censored","amp;tr":["udp%3A%2F%2Ftracker.openbittorrent.com%3A80","udp%3A%2F%2Fopen.demonii.com%3A1337","udp%3A%2F%2Ftracker.coppersurfer.tk%3A6969","udp%3A%2F%2Fexodus.desync.com%3A6969"],"infoHash":"0953340a33a9fcd3b8db8e4894d20cd74fc01cb8","infoHashBuffer":{"type":"Buffer","data":[9,83,52,10,51,169,252,211,184,219,142,72,148,210,12,215,79,192,28,184]},"announce":[],"urlList":[]}}