{"title":"Naked.Attraction.S01E04.HDTV.x264-C4TV","uid":15584131,"size":273698614,"categoryP":"video","categoryS":"tv_shows","magnet":"?xt=urn:btih:1995ffc607fceb2cf7c5a337e0d697e45eb43c85&amp;dn=Naked.Attraction.S01E04.HDTV.x264-C4TV&amp;tr=udp%3A%2F%2Ftracker.leechers-paradise.org%3A6969&amp;tr=udp%3A%2F%2Fzer0day.ch%3A1337&amp;tr=udp%3A%2F%2Fopen.demonii.com%3A1337&amp;tr=udp%3A%2F%2Ftracker.coppersurfer.tk%3A6969&amp;tr=udp%3A%2F%2Fexodus.desync.com%3A6969","seeders":1,"leechers":2,"uploader":"TvTeam","files":4,"time":1471443029,"description":"Torrent from:\r\n~~~~~~~~~~~~ \nhttps://www.torrenting.com\r\n\r\nJoin us and become part of the BIG family! Yarrrrrrrrrrrrrr!!!","torrent":{"xt":"urn:btih:1995ffc607fceb2cf7c5a337e0d697e45eb43c85","amp;dn":"Naked.Attraction.S01E04.HDTV.x264-C4TV","amp;tr":["udp%3A%2F%2Ftracker.leechers-paradise.org%3A6969","udp%3A%2F%2Fzer0day.ch%3A1337","udp%3A%2F%2Fopen.demonii.com%3A1337","udp%3A%2F%2Ftracker.coppersurfer.tk%3A6969","udp%3A%2F%2Fexodus.desync.com%3A6969"],"infoHash":"1995ffc607fceb2cf7c5a337e0d697e45eb43c85","infoHashBuffer":{"type":"Buffer","data":[25,149,255,198,7,252,235,44,247,197,163,55,224,214,151,228,94,180,60,133]},"announce":[],"urlList":[]}}