{"title":"zakladi tisocletij- rim","uid":5374091,"size":100979615,"categoryP":"other","categoryS":"e_books","magnet":"?xt=urn:btih:1c87eeb5a23197bac5a59538993178cf306bfffb&amp;dn=zakladi+tisocletij-+rim&amp;tr=udp%3A%2F%2Ftracker.openbittorrent.com%3A80&amp;tr=udp%3A%2F%2Fopen.demonii.com%3A1337&amp;tr=udp%3A%2F%2Ftracker.coppersurfer.tk%3A6969&amp;tr=udp%3A%2F%2Fexodus.desync.com%3A6969","seeders":1,"leechers":0,"uploader":null,"files":4,"time":1266517419,"description":"zakladi tisocletij &quot;samo&quot; rimski del","torrent":{"xt":"urn:btih:1c87eeb5a23197bac5a59538993178cf306bfffb","amp;dn":"zakladi+tisocletij-+rim","amp;tr":["udp%3A%2F%2Ftracker.openbittorrent.com%3A80","udp%3A%2F%2Fopen.demonii.com%3A1337","udp%3A%2F%2Ftracker.coppersurfer.tk%3A6969","udp%3A%2F%2Fexodus.desync.com%3A6969"],"infoHash":"1c87eeb5a23197bac5a59538993178cf306bfffb","infoHashBuffer":{"type":"Buffer","data":[28,135,238,181,162,49,151,186,197,165,149,56,153,49,120,207,48,107,255,251]},"announce":[],"urlList":[]}}