{"title":"Batwing 18 (2013) (Digital) (Shining Knight-SCC-Novus) [NVS-D]","uid":8227210,"size":12157942,"categoryP":"other","categoryS":"comics","magnet":"?xt=urn:btih:228003347686ca89a23499f42bde3a0f8fa8cadc&amp;dn=Batwing+18+%282013%29+%28Digital%29+%28Shining+Knight-SCC-Novus%29+%5BNVS-D%5D&amp;tr=udp%3A%2F%2Ftracker.openbittorrent.com%3A80&amp;tr=udp%3A%2F%2Fopen.demonii.com%3A1337&amp;tr=udp%3A%2F%2Ftracker.coppersurfer.tk%3A6969&amp;tr=udp%3A%2F%2Fexodus.desync.com%3A6969","seeders":1,"leechers":0,"uploader":"blackcanary","files":-1,"time":1362635840,"description":"English | CBR | 23 Pages\n\nBatwing #18\nPublisher:  DC Comics\nPublication Date:  March 6, 2013\n\nWritten by Fabian Nicieza\nArt and Cover by Fabrizio Fiorentino\nColors by Pete Pantazis\nLetters by Carlos M. Mangual\n\nBatwing learns the hard way that you can't bring justice to a country that doesn't want it! Plus: Batwing battles the Sky Pirate!\n\nThanks goes to Shining Knight for this release.\n &lt;a href=&quot;\nhttp://thepiratebay.se/torrent/7613225/Batwing_00_(2012)(Digital)(Shining_Knight-SCC-DCP)&quot; rel=&quot;nofollow&quot; target=&quot;_NEW&quot;&gt;\nhttp://thepiratebay.se/torrent/7613225/Batwing_00_(2012)(Digital)(Shining_Knight-SCC-DCP)&lt;/a&gt;\n &lt;a href=&quot;\nhttp://thepiratebay.se/torrent/7550505/Batwing_01-12_(DC_s_New_52)_(Digital)_(ShiningKnight-DCP)&quot; rel=&quot;nofollow&quot; target=&quot;_NEW&quot;&gt;\nhttp://thepiratebay.se/torrent/7550505/Batwing_01-12_(DC_s_New_52)_(Digital)_(ShiningKnight-DCP)&lt;/a&gt;\n &lt;a href=&quot;\nhttp://thepiratebay.se/torrent/8139902/Batwing_17_(2013)_(Digital)_(Shining_Knight-SCC-Novus)_[NVS-D]&quot; rel=&quot;nofollow&quot; target=&quot;_NEW&quot;&gt;\nhttp://thepiratebay.se/torrent/8139902/Batwing_17_(2013)_(Digital)_(Shining_Knight-SCC-Novus)_[NVS-D]&lt;/a&gt;","torrent":{"xt":"urn:btih:228003347686ca89a23499f42bde3a0f8fa8cadc","amp;dn":"Batwing+18+%282013%29+%28Digital%29+%28Shining+Knight-SCC-Novus%29+%5BNVS-D%5D","amp;tr":["udp%3A%2F%2Ftracker.openbittorrent.com%3A80","udp%3A%2F%2Fopen.demonii.com%3A1337","udp%3A%2F%2Ftracker.coppersurfer.tk%3A6969","udp%3A%2F%2Fexodus.desync.com%3A6969"],"infoHash":"228003347686ca89a23499f42bde3a0f8fa8cadc","infoHashBuffer":{"type":"Buffer","data":[34,128,3,52,118,134,202,137,162,52,153,244,43,222,58,15,143,168,202,220]},"announce":[],"urlList":[]}}