{"title":"MDC_051","uid":6348934,"size":40061684,"categoryP":"other","categoryS":"comics","magnet":"?xt=urn:btih:39a3a1cf7132dc29b2a98810913af543920b78be&amp;dn=MDC_051&amp;tr=udp%3A%2F%2Ftracker.openbittorrent.com%3A80&amp;tr=udp%3A%2F%2Fopen.demonii.com%3A1337&amp;tr=udp%3A%2F%2Ftracker.coppersurfer.tk%3A6969&amp;tr=udp%3A%2F%2Fexodus.desync.com%3A6969","seeders":1,"leechers":0,"uploader":"murdockgb","files":1,"time":1303930250,"description":"Tex - 088","torrent":{"xt":"urn:btih:39a3a1cf7132dc29b2a98810913af543920b78be","amp;dn":"MDC_051","amp;tr":["udp%3A%2F%2Ftracker.openbittorrent.com%3A80","udp%3A%2F%2Fopen.demonii.com%3A1337","udp%3A%2F%2Ftracker.coppersurfer.tk%3A6969","udp%3A%2F%2Fexodus.desync.com%3A6969"],"infoHash":"39a3a1cf7132dc29b2a98810913af543920b78be","infoHashBuffer":{"type":"Buffer","data":[57,163,161,207,113,50,220,41,178,169,136,16,145,58,245,67,146,11,120,190]},"announce":[],"urlList":[]}}