{"title":"I.Came.Inside.My.Sister.XXX.DVDRip.x264-XCiTE","uid":11459972,"size":1425750512,"categoryP":"porn","categoryS":"other","magnet":"?xt=urn:btih:3ba0047e7c8ef88b239a7c9a35c320aa94e6c192&amp;dn=I.Came.Inside.My.Sister.XXX.DVDRip.x264-XCiTE&amp;tr=udp%3A%2F%2Ftracker.openbittorrent.com%3A80&amp;tr=udp%3A%2F%2Fopen.demonii.com%3A1337&amp;tr=udp%3A%2F%2Ftracker.coppersurfer.tk%3A6969&amp;tr=udp%3A%2F%2Fexodus.desync.com%3A6969","seeders":1,"leechers":4,"uploader":"DrarbgXXX","files":5,"time":1415977073,"description":" &lt;a href=&quot;https://rarbg.com&quot; rel=&quot;nofollow&quot; target=&quot;_NEW&quot;&gt;https://rarbg.com&lt;/a&gt;\n\nI.Came.Inside.My.Sister.XXX.DVDRip.x264-XCiTE\n-----------------------------------------\nScreens : &lt;a href=&quot;\nhttp://imgcrl.org/v/92361276626425703915/&quot; rel=&quot;nofollow&quot; target=&quot;_NEW&quot;&gt;\nhttp://imgcrl.org/v/92361276626425703915/&lt;/a&gt;\n\n-----------------------------------------\nAuto Media Info :\nVideo Format........: AVC\nCodec ID............: avc1\nLength..............: 1h58mn\nVideo...............: 720x400 ( 23.976fps )\nBitrate.............: 1479Kbps\nAudio Format........: AAC\nCodec ID............: 40\nBit rate mode.......: Constant\nBitrate.............: 125Kbps\nChannel(s)..........: 2 channels","torrent":{"xt":"urn:btih:3ba0047e7c8ef88b239a7c9a35c320aa94e6c192","amp;dn":"I.Came.Inside.My.Sister.XXX.DVDRip.x264-XCiTE","amp;tr":["udp%3A%2F%2Ftracker.openbittorrent.com%3A80","udp%3A%2F%2Fopen.demonii.com%3A1337","udp%3A%2F%2Ftracker.coppersurfer.tk%3A6969","udp%3A%2F%2Fexodus.desync.com%3A6969"],"infoHash":"3ba0047e7c8ef88b239a7c9a35c320aa94e6c192","infoHashBuffer":{"type":"Buffer","data":[59,160,4,126,124,142,248,139,35,154,124,154,53,195,32,170,148,230,193,146]},"announce":[],"urlList":[]}}