{"title":"Hein Simons - Thuis (2014) NLToppers","uid":11135371,"size":110972494,"categoryP":"audio","categoryS":"other","magnet":"?xt=urn:btih:4af0b101527598b222a05322d54c940523f3e178&amp;dn=Hein+Simons+-+Thuis+%282014%29+NLToppers&amp;tr=udp%3A%2F%2Ftracker.openbittorrent.com%3A80&amp;tr=udp%3A%2F%2Fopen.demonii.com%3A1337&amp;tr=udp%3A%2F%2Ftracker.coppersurfer.tk%3A6969&amp;tr=udp%3A%2F%2Fexodus.desync.com%3A6969","seeders":1,"leechers":0,"uploader":"ore-sabre","files":-1,"time":1412104513,"description":"\n\n Hein Simons - Thuis (2014) NLToppers\n\n\n\nTracklist:\n\n\n01  In Onze Kleine Stamkroeg\n02. Gestolen Uren\n03. Achttien Lentes\n04. Jij En Ik\n05. De Vrouw Van Mijn Dromen\n06. Pure Waanzin\n07. Het Land Van Vondel En Piet Hein\n08. Luchtkasteel\n09. Vertrouw Op Jezelf\n10. Liefdesvuur\n11. Nooit Meer\n12. Ik Zeg Dank\n13. Medley\n\n\nPostinfo:\n\nCategorie : Sound\nType      : MP3 \nGenre     : Nederlands \nBitrate   : 320 Kbits \n\n   Ore-Sabre\n","torrent":{"xt":"urn:btih:4af0b101527598b222a05322d54c940523f3e178","amp;dn":"Hein+Simons+-+Thuis+%282014%29+NLToppers","amp;tr":["udp%3A%2F%2Ftracker.openbittorrent.com%3A80","udp%3A%2F%2Fopen.demonii.com%3A1337","udp%3A%2F%2Ftracker.coppersurfer.tk%3A6969","udp%3A%2F%2Fexodus.desync.com%3A6969"],"infoHash":"4af0b101527598b222a05322d54c940523f3e178","infoHashBuffer":{"type":"Buffer","data":[74,240,177,1,82,117,152,178,34,160,83,34,213,76,148,5,35,243,225,120]},"announce":[],"urlList":[]}}