{"title":"The Souls Of Inspyration (1970) [320k]","uid":8125574,"size":75583673,"categoryP":"audio","categoryS":"sound_clips","magnet":"?xt=urn:btih:4f4a89c31c9517b682f3b301616e8fdc757553f5&amp;dn=The+Souls+Of+Inspyration+%281970%29+%5B320k%5D&amp;tr=udp%3A%2F%2Ftracker.openbittorrent.com%3A80&amp;tr=udp%3A%2F%2Fopen.demonii.com%3A1337&amp;tr=udp%3A%2F%2Ftracker.coppersurfer.tk%3A6969&amp;tr=udp%3A%2F%2Fexodus.desync.com%3A6969","seeders":1,"leechers":1,"uploader":null,"files":12,"time":1360495368,"description":"The Souls Of Inspyration - The Souls Of Inspyration (1970)\n\nGenre: Canada, Psychedelic, Progressive Rock\n\nTracklist:\n\n01. Pursuit (Marc Paradis) - 2:43\n02. Stranger (John Maciejewski) - 3:00\n03. Sun Shines In Winter (Marc Paradis, Ray Cloutier) - 3:10\n04. Dil Kusha (Heart's Happiness) (Marc Paradis, John Maciejewski) - 6:42\n05. Of Lambs &amp; Wolves (Marc Paradis, John Maciejewski) - 6:09\n06. Eyes Of Nature (Marc Paradis, John Maciejewski) - 3:27\n07. Seasons Of Change (Marc Paradis, John Maciejewski) - 5:20\n\nBand:\n- John Maciejewski - lead guitar, lead vocals\n- Ray (Raymond) Cloutier - Hammond organ, piano, backing vocals\n- Don Wilson - bass\n- Marc Paradis - drums, backing vocals\n","torrent":{"xt":"urn:btih:4f4a89c31c9517b682f3b301616e8fdc757553f5","amp;dn":"The+Souls+Of+Inspyration+%281970%29+%5B320k%5D","amp;tr":["udp%3A%2F%2Ftracker.openbittorrent.com%3A80","udp%3A%2F%2Fopen.demonii.com%3A1337","udp%3A%2F%2Ftracker.coppersurfer.tk%3A6969","udp%3A%2F%2Fexodus.desync.com%3A6969"],"infoHash":"4f4a89c31c9517b682f3b301616e8fdc757553f5","infoHashBuffer":{"type":"Buffer","data":[79,74,137,195,28,149,23,182,130,243,179,1,97,110,143,220,117,117,83,245]},"announce":[],"urlList":[]}}