{"title":"Alcatraz S01E11 720p HDTV X264 DIMENSION [PHD]","uid":7115915,"size":1210145968,"categoryP":"video","categoryS":"hd___tv_shows","magnet":"?xt=urn:btih:520a468363c312a8b7ee24b0ced2c3a8815e94cf&amp;dn=Alcatraz+S01E11+720p+HDTV+X264+DIMENSION+%5BPHD%5D&amp;tr=udp%3A%2F%2Ftracker.openbittorrent.com%3A80&amp;tr=udp%3A%2F%2Fopen.demonii.com%3A1337&amp;tr=udp%3A%2F%2Ftracker.coppersurfer.tk%3A6969&amp;tr=udp%3A%2F%2Fexodus.desync.com%3A6969","seeders":1,"leechers":0,"uploader":"DibyaTPB","files":-1,"time":1332215527,"description":"Love or Hate Us You Can't Beat Us @ PublicHD . ORG\nYou Won't Find Every Thing But You Will Get Something\n\n-------------------------------------------------------------\n\n\nAlcatraz S01E11 720p HDTV X264 DIMENSION [PublicHD]\n\n\nSIZE...........: 1.13 GiB\nRUNTIME........: 43mn 13s\nVIDEO CODEC....: V_MPEG4/ISO/AVC\nRESOLUTION.....: 1280x720\nBITRATE........: 3 275 Kbps\nFRAMERATE......: 23.976 fps\nAUDIO.........2: AC-3 2 384 Kbps\n","torrent":{"xt":"urn:btih:520a468363c312a8b7ee24b0ced2c3a8815e94cf","amp;dn":"Alcatraz+S01E11+720p+HDTV+X264+DIMENSION+%5BPHD%5D","amp;tr":["udp%3A%2F%2Ftracker.openbittorrent.com%3A80","udp%3A%2F%2Fopen.demonii.com%3A1337","udp%3A%2F%2Ftracker.coppersurfer.tk%3A6969","udp%3A%2F%2Fexodus.desync.com%3A6969"],"infoHash":"520a468363c312a8b7ee24b0ced2c3a8815e94cf","infoHashBuffer":{"type":"Buffer","data":[82,10,70,131,99,195,18,168,183,238,36,176,206,210,195,168,129,94,148,207]},"announce":[],"urlList":[]}}