{"title":"The Clash - 1977-1993 [ALAC] (By Jamal The Moroccan)","uid":9803142,"size":3960513567,"categoryP":"audio","categoryS":"other","magnet":"?xt=urn:btih:56676bc7976d618b28fc2cabede16d023185330c&amp;dn=The+Clash+-+1977-1993+%5BALAC%5D+%28By+Jamal+The+Moroccan%29&amp;tr=udp%3A%2F%2Ftracker.openbittorrent.com%3A80&amp;tr=udp%3A%2F%2Fopen.demonii.com%3A1337&amp;tr=udp%3A%2F%2Ftracker.coppersurfer.tk%3A6969&amp;tr=udp%3A%2F%2Fexodus.desync.com%3A6969","seeders":1,"leechers":2,"uploader":"abdenna","files":177,"time":1395413952,"description":"The Clash - 1977-1993 [ALAC] (By Jamal The Moroccan)","torrent":{"xt":"urn:btih:56676bc7976d618b28fc2cabede16d023185330c","amp;dn":"The+Clash+-+1977-1993+%5BALAC%5D+%28By+Jamal+The+Moroccan%29","amp;tr":["udp%3A%2F%2Ftracker.openbittorrent.com%3A80","udp%3A%2F%2Fopen.demonii.com%3A1337","udp%3A%2F%2Ftracker.coppersurfer.tk%3A6969","udp%3A%2F%2Fexodus.desync.com%3A6969"],"infoHash":"56676bc7976d618b28fc2cabede16d023185330c","infoHashBuffer":{"type":"Buffer","data":[86,103,107,199,151,109,97,139,40,252,44,171,237,225,109,2,49,133,51,12]},"announce":[],"urlList":[]}}