{"title":"Brooklyn Chase - Cum In This Fat Pussy HD 720p","uid":11680645,"size":861889633,"categoryP":"porn","categoryS":"hd___movies","magnet":"?xt=urn:btih:5b5b90a89968a0dd9edb1c5418a97c081f67305f&amp;dn=Brooklyn+Chase+-+Cum+In+This+Fat+Pussy+HD+720p&amp;tr=udp%3A%2F%2Ftracker.openbittorrent.com%3A80&amp;tr=udp%3A%2F%2Fopen.demonii.com%3A1337&amp;tr=udp%3A%2F%2Ftracker.coppersurfer.tk%3A6969&amp;tr=udp%3A%2F%2Fexodus.desync.com%3A6969","seeders":1,"leechers":0,"uploader":"ElitePorn","files":1,"time":1423070244,"description":"Brooklyn Chase - Cum In This Fat Pussy HD 720p\n----------------------------------------------\n\nScreenshots:\n------------\n &lt;a href=&quot;\nhttp://picturescream.asia/soft/SqY&quot; rel=&quot;nofollow&quot; target=&quot;_NEW&quot;&gt;\nhttp://picturescream.asia/soft/SqY&lt;/a&gt;\n &lt;a href=&quot;\nhttp://picturescream.asia/soft/Squ&quot; rel=&quot;nofollow&quot; target=&quot;_NEW&quot;&gt;\nhttp://picturescream.asia/soft/Squ&lt;/a&gt;\n &lt;a href=&quot;\nhttp://picturescream.asia/soft/Sqv&quot; rel=&quot;nofollow&quot; target=&quot;_NEW&quot;&gt;\nhttp://picturescream.asia/soft/Sqv&lt;/a&gt;\n &lt;a href=&quot;\nhttp://picturescream.asia/soft/SqM&quot; rel=&quot;nofollow&quot; target=&quot;_NEW&quot;&gt;\nhttp://picturescream.asia/soft/SqM&lt;/a&gt;\n &lt;a href=&quot;\nhttp://picturescream.asia/soft/SqP&quot; rel=&quot;nofollow&quot; target=&quot;_NEW&quot;&gt;\nhttp://picturescream.asia/soft/SqP&lt;/a&gt;\n &lt;a href=&quot;\nhttp://picturescream.asia/soft/Sqm&quot; rel=&quot;nofollow&quot; target=&quot;_NEW&quot;&gt;\nhttp://picturescream.asia/soft/Sqm&lt;/a&gt;\n\n\nDuration: 44:43, Format: mp4, Resolution: 1280x720, Size: 821.96 MB\n\n...~~~:::For More Porn Torrents:::~~~...   &lt;a href=&quot;\nhttps://thepiratebay.se/user/ElitePorn/&quot; rel=&quot;nofollow&quot; target=&quot;_NEW&quot;&gt;\nhttps://thepiratebay.se/user/ElitePorn/&lt;/a&gt;","torrent":{"xt":"urn:btih:5b5b90a89968a0dd9edb1c5418a97c081f67305f","amp;dn":"Brooklyn+Chase+-+Cum+In+This+Fat+Pussy+HD+720p","amp;tr":["udp%3A%2F%2Ftracker.openbittorrent.com%3A80","udp%3A%2F%2Fopen.demonii.com%3A1337","udp%3A%2F%2Ftracker.coppersurfer.tk%3A6969","udp%3A%2F%2Fexodus.desync.com%3A6969"],"infoHash":"5b5b90a89968a0dd9edb1c5418a97c081f67305f","infoHashBuffer":{"type":"Buffer","data":[91,91,144,168,153,104,160,221,158,219,28,84,24,169,124,8,31,103,48,95]},"announce":[],"urlList":[]}}