{"title":"Me-Neibor MrsChawla rides me wth her sexy ass indian","uid":13503107,"size":129483984,"categoryP":"porn","categoryS":"movie_clips","magnet":"?xt=urn:btih:5e77ec7f89d2c6c8a1331e27b5b2c96b40e03136&amp;dn=Me-Neibor+MrsChawla+rides+me+wth+her+sexy+ass+indian&amp;tr=udp%3A%2F%2Ftracker.leechers-paradise.org%3A6969&amp;tr=udp%3A%2F%2Fzer0day.ch%3A1337&amp;tr=udp%3A%2F%2Fopen.demonii.com%3A1337&amp;tr=udp%3A%2F%2Ftracker.coppersurfer.tk%3A6969&amp;tr=udp%3A%2F%2Fexodus.desync.com%3A6969","seeders":1,"leechers":0,"uploader":"demonoidt","files":1,"time":1455225506,"description":"Samples\r\n \nhttp://adultwallpapers.co.in/me-neibor-mrschawla-rides-me-wth-her-sexy-ass/\r\n \nhttp://adultwallpapers.co.in/me-neibor-mrschawla-rides-me-wth-her-sexy-ass-2/\r\n \nhttp://adultwallpapers.co.in/me-neibor-mrschawla-rides-me-wth-her-sexy-ass-3/\r\n \nhttp://demonoid.co/2016/02/11/me-neibor-mrschawla-rides-me-wth-her-sexy-ass/","torrent":{"xt":"urn:btih:5e77ec7f89d2c6c8a1331e27b5b2c96b40e03136","amp;dn":"Me-Neibor+MrsChawla+rides+me+wth+her+sexy+ass+indian","amp;tr":["udp%3A%2F%2Ftracker.leechers-paradise.org%3A6969","udp%3A%2F%2Fzer0day.ch%3A1337","udp%3A%2F%2Fopen.demonii.com%3A1337","udp%3A%2F%2Ftracker.coppersurfer.tk%3A6969","udp%3A%2F%2Fexodus.desync.com%3A6969"],"infoHash":"5e77ec7f89d2c6c8a1331e27b5b2c96b40e03136","infoHashBuffer":{"type":"Buffer","data":[94,119,236,127,137,210,198,200,161,51,30,39,181,178,201,107,64,224,49,54]},"announce":[],"urlList":[]}}