{"title":"HDTeenies - Kiara","uid":8568456,"size":308149965,"categoryP":"porn","categoryS":"movie_clips","magnet":"?xt=urn:btih:60c47bb702e71cee79599460b6c9d17830b1539f&amp;dn=HDTeenies+-+Kiara&amp;tr=udp%3A%2F%2Ftracker.openbittorrent.com%3A80&amp;tr=udp%3A%2F%2Fopen.demonii.com%3A1337&amp;tr=udp%3A%2F%2Ftracker.coppersurfer.tk%3A6969&amp;tr=udp%3A%2F%2Fexodus.desync.com%3A6969","seeders":1,"leechers":0,"uploader":"R0thschild","files":1,"time":1371076934,"description":"********************************************\nGallery:  &lt;a href=&quot;\nhttp://publichash.com/index.php?page=torrent-details&amp;id=60c47bb702e71cee79599460b6c9d17830b1539f&quot; rel=&quot;nofollow&quot; target=&quot;_NEW&quot;&gt;\nhttp://publichash.com/index.php?page=torrent-details&amp;id=60c47bb702e71cee79599460b6c9d17830b1539f&lt;/a&gt;\n\n********************************************\t","torrent":{"xt":"urn:btih:60c47bb702e71cee79599460b6c9d17830b1539f","amp;dn":"HDTeenies+-+Kiara","amp;tr":["udp%3A%2F%2Ftracker.openbittorrent.com%3A80","udp%3A%2F%2Fopen.demonii.com%3A1337","udp%3A%2F%2Ftracker.coppersurfer.tk%3A6969","udp%3A%2F%2Fexodus.desync.com%3A6969"],"infoHash":"60c47bb702e71cee79599460b6c9d17830b1539f","infoHashBuffer":{"type":"Buffer","data":[96,196,123,183,2,231,28,238,121,89,148,96,182,201,209,120,48,177,83,159]},"announce":[],"urlList":[]}}