{"title":"Mad Sex Party Facial Fantasies - Trisha.avi","uid":7682181,"size":126401992,"categoryP":"porn","categoryS":"movie_clips","magnet":"?xt=urn:btih:65e5111da99c082e04b71e59dba56b586baa7ee1&amp;dn=Mad+Sex+Party+Facial+Fantasies+-+Trisha.avi&amp;tr=udp%3A%2F%2Ftracker.openbittorrent.com%3A80&amp;tr=udp%3A%2F%2Fopen.demonii.com%3A1337&amp;tr=udp%3A%2F%2Ftracker.coppersurfer.tk%3A6969&amp;tr=udp%3A%2F%2Fexodus.desync.com%3A6969","seeders":1,"leechers":1,"uploader":"Pornmaze","files":-1,"time":1348850145,"description":"Mad Sex Party Facial Fantasies - Trisha.avi\n\n2010, Bukkake, All Sex, Gang Bang, Hardcore, Oral, XXX, Adult\n\n576 x 320\n\n00:17:25\n\n120.55 MB \n\nScreens\n &lt;a href=&quot;\nhttp://www.pixsor.com/share-DFE3_5065B88E.html&quot; rel=&quot;nofollow&quot; target=&quot;_NEW&quot;&gt;\nhttp://www.pixsor.com/share-DFE3_5065B88E.html&lt;/a&gt;\n &lt;a href=&quot;\nhttp://www.pixsor.com/share-7A27_5065B88E.html&quot; rel=&quot;nofollow&quot; target=&quot;_NEW&quot;&gt;\nhttp://www.pixsor.com/share-7A27_5065B88E.html&lt;/a&gt;","torrent":{"xt":"urn:btih:65e5111da99c082e04b71e59dba56b586baa7ee1","amp;dn":"Mad+Sex+Party+Facial+Fantasies+-+Trisha.avi","amp;tr":["udp%3A%2F%2Ftracker.openbittorrent.com%3A80","udp%3A%2F%2Fopen.demonii.com%3A1337","udp%3A%2F%2Ftracker.coppersurfer.tk%3A6969","udp%3A%2F%2Fexodus.desync.com%3A6969"],"infoHash":"65e5111da99c082e04b71e59dba56b586baa7ee1","infoHashBuffer":{"type":"Buffer","data":[101,229,17,29,169,156,8,46,4,183,30,89,219,165,107,88,107,170,126,225]},"announce":[],"urlList":[]}}