{"title":"DC Talk - 1998 - My Friend (So Long) Single","uid":4872840,"size":13177326,"categoryP":"audio","categoryS":"music","magnet":"?xt=urn:btih:6f5b116b61d0de77c476d17d0d204f552ee2a547&amp;dn=DC+Talk+-+1998+-+My+Friend+%28So+Long%29+Single&amp;tr=udp%3A%2F%2Ftracker.openbittorrent.com%3A80&amp;tr=udp%3A%2F%2Fopen.demonii.com%3A1337&amp;tr=udp%3A%2F%2Ftracker.coppersurfer.tk%3A6969&amp;tr=udp%3A%2F%2Fexodus.desync.com%3A6969","seeders":1,"leechers":2,"uploader":"TorrentTracts","files":3,"time":1240934977,"description":"DC Talk - 1998 - My Friend (So Long) Single\n\n\nTRACK LISTING:\n\n01 - My Friend (So Long)\n02 - Colored People (Live)\n03 - Jesus Freak (Freaked Out Remix)\n\n\nTORRENTED BY:\n\nTorrent Tracts, April 2009\n\n\n","torrent":{"xt":"urn:btih:6f5b116b61d0de77c476d17d0d204f552ee2a547","amp;dn":"DC+Talk+-+1998+-+My+Friend+%28So+Long%29+Single","amp;tr":["udp%3A%2F%2Ftracker.openbittorrent.com%3A80","udp%3A%2F%2Fopen.demonii.com%3A1337","udp%3A%2F%2Ftracker.coppersurfer.tk%3A6969","udp%3A%2F%2Fexodus.desync.com%3A6969"],"infoHash":"6f5b116b61d0de77c476d17d0d204f552ee2a547","infoHashBuffer":{"type":"Buffer","data":[111,91,17,107,97,208,222,119,196,118,209,125,13,32,79,85,46,226,165,71]},"announce":[],"urlList":[]}}