{"title":"Teen Fidelitys Deep Cream Pies 4.DVDRip.XxX","uid":9148803,"size":2412095488,"categoryP":"porn","categoryS":"movies","magnet":"?xt=urn:btih:847b2519671743b96f9cba1b5e00ca5c7c378278&amp;dn=Teen+Fidelitys+Deep+Cream+Pies+4.DVDRip.XxX&amp;tr=udp%3A%2F%2Ftracker.openbittorrent.com%3A80&amp;tr=udp%3A%2F%2Fopen.demonii.com%3A1337&amp;tr=udp%3A%2F%2Ftracker.coppersurfer.tk%3A6969&amp;tr=udp%3A%2F%2Fexodus.desync.com%3A6969","seeders":1,"leechers":0,"uploader":"handsome_hulk1253","files":1,"time":1383635429,"description":"Screenshots\n &lt;a href=&quot;\nhttp://adultxpictures.com/xxx/69l&quot; rel=&quot;nofollow&quot; target=&quot;_NEW&quot;&gt;\nhttp://adultxpictures.com/xxx/69l&lt;/a&gt; &lt;a href=&quot;\nhttp://adultxpictures.com/xxx/69x&quot; rel=&quot;nofollow&quot; target=&quot;_NEW&quot;&gt;\nhttp://adultxpictures.com/xxx/69x&lt;/a&gt;","torrent":{"xt":"urn:btih:847b2519671743b96f9cba1b5e00ca5c7c378278","amp;dn":"Teen+Fidelitys+Deep+Cream+Pies+4.DVDRip.XxX","amp;tr":["udp%3A%2F%2Ftracker.openbittorrent.com%3A80","udp%3A%2F%2Fopen.demonii.com%3A1337","udp%3A%2F%2Ftracker.coppersurfer.tk%3A6969","udp%3A%2F%2Fexodus.desync.com%3A6969"],"infoHash":"847b2519671743b96f9cba1b5e00ca5c7c378278","infoHashBuffer":{"type":"Buffer","data":[132,123,37,25,103,23,67,185,111,156,186,27,94,0,202,92,124,55,130,120]},"announce":[],"urlList":[]}}