{"title":"Lasting Summer (Loving Summer #5) - Kailin Gow","uid":11012490,"size":2693721,"categoryP":"other","categoryS":"e_books","magnet":"?xt=urn:btih:8591ae735747a223cbeb307a886f1a93c3d58615&amp;dn=Lasting+Summer+%28Loving+Summer+%235%29+-+Kailin+Gow&amp;tr=udp%3A%2F%2Ftracker.openbittorrent.com%3A80&amp;tr=udp%3A%2F%2Fopen.demonii.com%3A1337&amp;tr=udp%3A%2F%2Ftracker.coppersurfer.tk%3A6969&amp;tr=udp%3A%2F%2Fexodus.desync.com%3A6969","seeders":1,"leechers":1,"uploader":"DethHolly","files":6,"time":1410387686,"description":"Summer Jones thought she lost Nat Donovan, the boy she had always had a crush on since she could remember, when he went off on a mission to find his father, the founder and CEO of Donovan Dynamics, the billion dollar security and intelligence corporation who is now protecting her from the stalker who has attempted to kill her twice. \n\nHe had always been her rock, had always been there for her, but now Nat has disappeared. According to Donovan Dynamics, it was for good.\n\nCould Summer continue on? Could Nat's playboy one-night stand legend brother Drew Donovan live up to Nat's legacy as the family's perfect son, as the one who could eventually run Donovan Dynamics? With Nat gone, could he finally get Summer to commit to him with all her heart and soul?\n\nAll the secrets, all the heartaches, come out in Lasting Summer as the Donovans and Summer learn to deal with the truth about Nat, Drew, and Summer that will test each others' love to each other and to family.\n\n- - -\n\nFormats: EPUB, MOBI, AZW3, PDF\nASIN#: B00NDYD9UI\nISBN#: 1597481114\nISBN13#: 9781597481113\nPublished: September 8th, 2014\nLanguage: English","torrent":{"xt":"urn:btih:8591ae735747a223cbeb307a886f1a93c3d58615","amp;dn":"Lasting+Summer+%28Loving+Summer+%235%29+-+Kailin+Gow","amp;tr":["udp%3A%2F%2Ftracker.openbittorrent.com%3A80","udp%3A%2F%2Fopen.demonii.com%3A1337","udp%3A%2F%2Ftracker.coppersurfer.tk%3A6969","udp%3A%2F%2Fexodus.desync.com%3A6969"],"infoHash":"8591ae735747a223cbeb307a886f1a93c3d58615","infoHashBuffer":{"type":"Buffer","data":[133,145,174,115,87,71,162,35,203,235,48,122,136,111,26,147,195,213,134,21]},"announce":[],"urlList":[]}}