{"title":"Ip Man The Final Fight 2013 720p BRRip XviD AC3-RARBG","uid":9201284,"size":2969674384,"categoryP":"video","categoryS":"hd___movies","magnet":"?xt=urn:btih:a8b3b3112e01ea13a630954e32bb52283208d45e&amp;dn=Ip+Man+The+Final+Fight+2013+720p+BRRip+XviD+AC3-RARBG&amp;tr=udp%3A%2F%2Ftracker.openbittorrent.com%3A80&amp;tr=udp%3A%2F%2Fopen.demonii.com%3A1337&amp;tr=udp%3A%2F%2Ftracker.coppersurfer.tk%3A6969&amp;tr=udp%3A%2F%2Fexodus.desync.com%3A6969","seeders":1,"leechers":0,"uploader":"Drarbg","files":4,"time":1384598046,"description":"Ip Man The Final Fight 2013 720p BRRip XviD AC3-RARBG\n-----------------------------------------\nScreens : &lt;a href=&quot;\nhttp://i.imgur.com/ASr1jTv.jpg&quot; rel=&quot;nofollow&quot; target=&quot;_NEW&quot;&gt;\nhttp://i.imgur.com/ASr1jTv.jpg&lt;/a&gt; &lt;a href=&quot;\nhttp://i.imgur.com/0A4fhsh.jpg&quot; rel=&quot;nofollow&quot; target=&quot;_NEW&quot;&gt;\nhttp://i.imgur.com/0A4fhsh.jpg&lt;/a&gt; &lt;a href=&quot;\nhttp://i.imgur.com/bzYROfd.jpg&quot; rel=&quot;nofollow&quot; target=&quot;_NEW&quot;&gt;\nhttp://i.imgur.com/bzYROfd.jpg&lt;/a&gt; &lt;a href=&quot;\nhttp://i.imgur.com/rHHHki2.png&quot; rel=&quot;nofollow&quot; target=&quot;_NEW&quot;&gt;\nhttp://i.imgur.com/rHHHki2.png&lt;/a&gt; &lt;a href=&quot;\nhttp://i.imgur.com/C9nXosk.jpg&quot; rel=&quot;nofollow&quot; target=&quot;_NEW&quot;&gt;\nhttp://i.imgur.com/C9nXosk.jpg&lt;/a&gt; &lt;a href=&quot;\nhttp://i.imgur.com/YbfVYBE.png&quot; rel=&quot;nofollow&quot; target=&quot;_NEW&quot;&gt;\nhttp://i.imgur.com/YbfVYBE.png&lt;/a&gt;\n\n","torrent":{"xt":"urn:btih:a8b3b3112e01ea13a630954e32bb52283208d45e","amp;dn":"Ip+Man+The+Final+Fight+2013+720p+BRRip+XviD+AC3-RARBG","amp;tr":["udp%3A%2F%2Ftracker.openbittorrent.com%3A80","udp%3A%2F%2Fopen.demonii.com%3A1337","udp%3A%2F%2Ftracker.coppersurfer.tk%3A6969","udp%3A%2F%2Fexodus.desync.com%3A6969"],"infoHash":"a8b3b3112e01ea13a630954e32bb52283208d45e","infoHashBuffer":{"type":"Buffer","data":[168,179,179,17,46,1,234,19,166,48,149,78,50,187,82,40,50,8,212,94]},"announce":[],"urlList":[]}}