{"title":"Little Big Town - Leavin' In Your Eyes.mpg","uid":8505991,"size":132749316,"categoryP":"video","categoryS":"music_videos","magnet":"?xt=urn:btih:a8bf1c942c6a87571682d79414c59bcc70c3b266&amp;dn=Little+Big+Town+-+Leavin%27+In+Your+Eyes.mpg&amp;tr=udp%3A%2F%2Ftracker.openbittorrent.com%3A80&amp;tr=udp%3A%2F%2Fopen.demonii.com%3A1337&amp;tr=udp%3A%2F%2Ftracker.coppersurfer.tk%3A6969&amp;tr=udp%3A%2F%2Fexodus.desync.com%3A6969","seeders":1,"leechers":0,"uploader":"Ashja","files":1,"time":1369424410,"description":"  File Info: Country \n\nVideo: MPEG-2 video , 720x480, 29.97 fps, VBR (Constant quality), Maximum 5200 Kb/s\nAudio: Dolby Digital, 48000 Hz, Stereo, 192 kbps","torrent":{"xt":"urn:btih:a8bf1c942c6a87571682d79414c59bcc70c3b266","amp;dn":"Little+Big+Town+-+Leavin%27+In+Your+Eyes.mpg","amp;tr":["udp%3A%2F%2Ftracker.openbittorrent.com%3A80","udp%3A%2F%2Fopen.demonii.com%3A1337","udp%3A%2F%2Ftracker.coppersurfer.tk%3A6969","udp%3A%2F%2Fexodus.desync.com%3A6969"],"infoHash":"a8bf1c942c6a87571682d79414c59bcc70c3b266","infoHashBuffer":{"type":"Buffer","data":[168,191,28,148,44,106,135,87,22,130,215,148,20,197,155,204,112,195,178,102]},"announce":[],"urlList":[]}}