{"title":"Lan.Viewer.v1.62.WinALL-BRD","uid":3530370,"size":1066857,"categoryP":"applications","categoryS":"windows","magnet":"?xt=urn:btih:d0a693c8bd314a25ea2f9809c34524b99155af63&amp;dn=Lan.Viewer.v1.62.WinALL-BRD&amp;tr=udp%3A%2F%2Ftracker.openbittorrent.com%3A80&amp;tr=udp%3A%2F%2Fopen.demonii.com%3A1337&amp;tr=udp%3A%2F%2Ftracker.coppersurfer.tk%3A6969&amp;tr=udp%3A%2F%2Fexodus.desync.com%3A6969","seeders":1,"leechers":0,"uploader":"masseur","files":2,"time":1159390064,"description":"brought to you by\n &lt;a href=&quot;\nhttp://www.NewTorrents.info&quot; rel=&quot;nofollow&quot; target=&quot;_NEW&quot;&gt;\nhttp://www.NewTorrents.info&lt;/a&gt;\n\n\n\n\n\n\ncheck out our other sites too!\n\n &lt;a href=&quot;\nhttp://www.RLSLOG.net&quot; rel=&quot;nofollow&quot; target=&quot;_NEW&quot;&gt;\nhttp://www.RLSLOG.net&lt;/a&gt; - Releaselog\n &lt;a href=&quot;\nhttp://www.Leechers.info&quot; rel=&quot;nofollow&quot; target=&quot;_NEW&quot;&gt;\nhttp://www.Leechers.info&lt;/a&gt; - Leecher&amp;#039;s Lair","torrent":{"xt":"urn:btih:d0a693c8bd314a25ea2f9809c34524b99155af63","amp;dn":"Lan.Viewer.v1.62.WinALL-BRD","amp;tr":["udp%3A%2F%2Ftracker.openbittorrent.com%3A80","udp%3A%2F%2Fopen.demonii.com%3A1337","udp%3A%2F%2Ftracker.coppersurfer.tk%3A6969","udp%3A%2F%2Fexodus.desync.com%3A6969"],"infoHash":"d0a693c8bd314a25ea2f9809c34524b99155af63","infoHashBuffer":{"type":"Buffer","data":[208,166,147,200,189,49,74,37,234,47,152,9,195,69,36,185,145,85,175,99]},"announce":[],"urlList":[]}}