{"title":"American.Idol.S13E31.720p.HDTV.x264-2HD [PublicHD]","uid":10037386,"size":804105336,"categoryP":"video","categoryS":"hd___tv_shows","magnet":"?xt=urn:btih:d74fd9086c8f3989efd0a6eddda50e931a43b89c&amp;dn=American.Idol.S13E31.720p.HDTV.x264-2HD+%5BPublicHD%5D&amp;tr=udp%3A%2F%2Ftracker.openbittorrent.com%3A80&amp;tr=udp%3A%2F%2Fopen.demonii.com%3A1337&amp;tr=udp%3A%2F%2Ftracker.coppersurfer.tk%3A6969&amp;tr=udp%3A%2F%2Fexodus.desync.com%3A6969","seeders":1,"leechers":0,"uploader":"DibyaTPB","files":2,"time":1398419697,"description":"\n                PublicHD - High-Definition Bittorrent Community\n      \n                               \n              ----------------------------------------------------\n\nAmerican.Idol.S13E31.720p.HDTV.x264-2HD [PublicHD]\n \nLength..............: 20mn 24s\nVideo...............: H264 @ 5252Kbps (1280x720)\nFPS.................: 29.970 FPS\nAudio...............: AC3\n\n\n\nSCREENS &lt;a href=&quot;\nhttp://istoreimg.com/i/535a138670564.html&quot; rel=&quot;nofollow&quot; target=&quot;_NEW&quot;&gt;\nhttp://istoreimg.com/i/535a138670564.html&lt;/a&gt; &lt;a href=&quot;\nhttp://istoreimg.com/i/535a1386a6d6e.html&quot; rel=&quot;nofollow&quot; target=&quot;_NEW&quot;&gt;\nhttp://istoreimg.com/i/535a1386a6d6e.html&lt;/a&gt; &lt;a href=&quot;\nhttp://istoreimg.com/i/535a1387062bd.html&quot; rel=&quot;nofollow&quot; target=&quot;_NEW&quot;&gt;\nhttp://istoreimg.com/i/535a1387062bd.html&lt;/a&gt; &lt;a href=&quot;\nhttp://istoreimg.com/i/535a138740568.html&quot; rel=&quot;nofollow&quot; target=&quot;_NEW&quot;&gt;\nhttp://istoreimg.com/i/535a138740568.html&lt;/a&gt; &lt;a href=&quot;\nhttp://istoreimg.com/i/535a13876fa55.html&quot; rel=&quot;nofollow&quot; target=&quot;_NEW&quot;&gt;\nhttp://istoreimg.com/i/535a13876fa55.html&lt;/a&gt; &lt;a href=&quot;\nhttp://istoreimg.com/i/535a1387c60ef.html&quot; rel=&quot;nofollow&quot; target=&quot;_NEW&quot;&gt;\nhttp://istoreimg.com/i/535a1387c60ef.html&lt;/a&gt; ","torrent":{"xt":"urn:btih:d74fd9086c8f3989efd0a6eddda50e931a43b89c","amp;dn":"American.Idol.S13E31.720p.HDTV.x264-2HD+%5BPublicHD%5D","amp;tr":["udp%3A%2F%2Ftracker.openbittorrent.com%3A80","udp%3A%2F%2Fopen.demonii.com%3A1337","udp%3A%2F%2Ftracker.coppersurfer.tk%3A6969","udp%3A%2F%2Fexodus.desync.com%3A6969"],"infoHash":"d74fd9086c8f3989efd0a6eddda50e931a43b89c","infoHashBuffer":{"type":"Buffer","data":[215,79,217,8,108,143,57,137,239,208,166,237,221,165,14,147,26,67,184,156]},"announce":[],"urlList":[]}}