{"title":"EPL - Wigan Athletic vs Liverpool 2.3.2013","uid":8214918,"size":1143974585,"categoryP":"video","categoryS":"tv_shows","magnet":"?xt=urn:btih:e24ff903ec8babb7399c5ffd960a14e97e184143&amp;dn=EPL+-+Wigan+Athletic+vs+Liverpool+2.3.2013&amp;tr=udp%3A%2F%2Ftracker.openbittorrent.com%3A80&amp;tr=udp%3A%2F%2Fopen.demonii.com%3A1337&amp;tr=udp%3A%2F%2Ftracker.coppersurfer.tk%3A6969&amp;tr=udp%3A%2F%2Fexodus.desync.com%3A6969","seeders":1,"leechers":0,"uploader":"Demonoid4Ever","files":2,"time":1362323674,"description":"EPL - Wigan Athletic vs Liverpool 2.3.2013\nVideo : AVC, 25 fps, 704 x 400, 1536 Kbps\nAudio Track: English (AAC, 48 kHz 128 kb/s)\ncredit: Paolo\t\n\n","torrent":{"xt":"urn:btih:e24ff903ec8babb7399c5ffd960a14e97e184143","amp;dn":"EPL+-+Wigan+Athletic+vs+Liverpool+2.3.2013","amp;tr":["udp%3A%2F%2Ftracker.openbittorrent.com%3A80","udp%3A%2F%2Fopen.demonii.com%3A1337","udp%3A%2F%2Ftracker.coppersurfer.tk%3A6969","udp%3A%2F%2Fexodus.desync.com%3A6969"],"infoHash":"e24ff903ec8babb7399c5ffd960a14e97e184143","infoHashBuffer":{"type":"Buffer","data":[226,79,249,3,236,139,171,183,57,156,95,253,150,10,20,233,126,24,65,67]},"announce":[],"urlList":[]}}