{"title":"Sexy Saffron Bacchus Surprise Sensual Blowjob foot/panty hose","uid":11811460,"size":164196166,"categoryP":"porn","categoryS":"movie_clips","magnet":"?xt=urn:btih:fccc058b156e518654c1cd6792860ab3cf354238&amp;dn=Sexy+Saffron+Bacchus+Surprise+Sensual+Blowjob+foot%2Fpanty+hose+&amp;tr=udp%3A%2F%2Ftracker.openbittorrent.com%3A80&amp;tr=udp%3A%2F%2Fopen.demonii.com%3A1337&amp;tr=udp%3A%2F%2Ftracker.coppersurfer.tk%3A6969&amp;tr=udp%3A%2F%2Fexodus.desync.com%3A6969","seeders":1,"leechers":1,"uploader":"sunny1969","files":1,"time":1428822992,"description":"Sexy Saffron Bacchus Surprise Sensual Blowjob.\n\nThis is a great one for those of you with a foot and/or panty hose fetish.  See the image sample.  Saffron Bacchus is an amateur fetish model/home porn star who makes videos with her husband.\n\n\nImage sample: &lt;a href=&quot; http://postimg.org/image/l83s3o1q7/&quot; rel=&quot;nofollow&quot; target=&quot;_NEW&quot;&gt; http://postimg.org/image/l83s3o1q7/&lt;/a&gt;\n\nPlease Seed!","torrent":{"xt":"urn:btih:fccc058b156e518654c1cd6792860ab3cf354238","amp;dn":"Sexy+Saffron+Bacchus+Surprise+Sensual+Blowjob+foot%2Fpanty+hose+","amp;tr":["udp%3A%2F%2Ftracker.openbittorrent.com%3A80","udp%3A%2F%2Fopen.demonii.com%3A1337","udp%3A%2F%2Ftracker.coppersurfer.tk%3A6969","udp%3A%2F%2Fexodus.desync.com%3A6969"],"infoHash":"fccc058b156e518654c1cd6792860ab3cf354238","infoHashBuffer":{"type":"Buffer","data":[252,204,5,139,21,110,81,134,84,193,205,103,146,134,10,179,207,53,66,56]},"announce":[],"urlList":[]}}