{"title":"One.For.The.Money.2012.720p.BluRay.x264-Rx","uid":7066501,"size":5967061880,"categoryP":"video","categoryS":"hd___movies","magnet":"?xt=urn:btih:fed590d4c04e381f2826090477a2c1241cc4052d&amp;dn=One.For.The.Money.2012.720p.BluRay.x264-Rx&amp;tr=udp%3A%2F%2Ftracker.openbittorrent.com%3A80&amp;tr=udp%3A%2F%2Fopen.demonii.com%3A1337&amp;tr=udp%3A%2F%2Ftracker.coppersurfer.tk%3A6969&amp;tr=udp%3A%2F%2Fexodus.desync.com%3A6969","seeders":1,"leechers":0,"uploader":"WORD7BBC","files":-1,"time":1330531845,"description":"\n\nOne.For.The.Money.2012.720p.BluRay.x264-Rx\n\nUnemployed and newly-divorced Stephanie Plum lands a job at her cousin's bail-bond business, where her first assignment puts her on the trail of a wanted local cop from her romantic past. \n\n Director: Julie Anne Robinson\n Writers: Stacy Sherman (screenplay), Karen Ray (screenplay),  and 2 more credits Ã‚Â» \nStars: Katherine Heigl, Jason O'Mara and Daniel Sunjata\n\n\n &lt;a href=&quot; http://www.imdb.com/title/tt1598828/&quot; rel=&quot;nofollow&quot; target=&quot;_NEW&quot;&gt; http://www.imdb.com/title/tt1598828/&lt;/a&gt;\n\n\nINFO:\n\n\nOne.For.The.Money.2012.720p.BluRay.x264-Rx\n\n\n\n Basic Information\n\n -----------------\n\n Container.......: MKV\n\n Size............: 6.56 GiB\n\n Duration........: 1h 31mn\n\n Overall.Bitrate.: 6 849 Kbps\n\n Framerate.......: 23.976 Fps\n\n Subs.Included...: NO \n\n Sample.Included.: YES\n\n Release.Date....: 02/29/2012\n\n\n\n Video Information\n\n -----------------\n\n Video.Format....: AVC\n\n Video.Bitrate...: 5 339 Kbps\n\n Dimensions......: 1280x536\n\n Aspect.Ratio....: 2.39:1\n\n\n\n Audio Information\n\n -----------------\n\n Audio.Format....: DTS\n\n Audio.Bitrate...: 1 510 Kbps\n\n Channels........: 6\n\n Language........: English\n\n\n\n Movie Information                                                       \n\n -----------------                                                       \n\n Release.Year....: 2012\n\n Genre...........: Action | Comedy | Crime \n\n IMDB............: http://www.imdb.com/title/tt1598828/\n\n\n\n Release Notes\n\n -------------\n\n Source....: BluRay","torrent":{"xt":"urn:btih:fed590d4c04e381f2826090477a2c1241cc4052d","amp;dn":"One.For.The.Money.2012.720p.BluRay.x264-Rx","amp;tr":["udp%3A%2F%2Ftracker.openbittorrent.com%3A80","udp%3A%2F%2Fopen.demonii.com%3A1337","udp%3A%2F%2Ftracker.coppersurfer.tk%3A6969","udp%3A%2F%2Fexodus.desync.com%3A6969"],"infoHash":"fed590d4c04e381f2826090477a2c1241cc4052d","infoHashBuffer":{"type":"Buffer","data":[254,213,144,212,192,78,56,31,40,38,9,4,119,162,193,36,28,196,5,45]},"announce":[],"urlList":[]}}